[
  { 
    "版本": "v1.0.3", 
    "日期": "2026-07-22", 
    "内容": 
    [
      "1.新增了关卡: 4 5",
      "2.新增了版本检测功能,用于检测当前版本是否为最新版本.",
      "3.添加了部分按钮音效.",
      "4.修复了游戏图标错误的问题.",
      "5.修复了钉子方向错误的问题.",
      "6.修复了第二关钉子数量错误的问题.",
      "7.修复了第三关钉子数量缺失的问题.",
      "8.修复了退出创作面模式后再次开始闯关时无法移除钉子的问题.",
      "9.修复了钉盒和广告盒比例不一致的问题.",
      "10.修复了创作模式更改积木颜色没有同步更新的问题.",
      "11.修复了创作模式钉子数量没有及时更新的问题.",
      "12.关闭了安卓四指开启控制台.",
      "13.移除了屏幕下方的两个虚拟摇杆.",
      "14.移除了游戏初始引擎展示页面."
    ] 
  },
  { 
    "版本": "v1.0.2", 
    "日期": "2026-07-18", 
    "内容": 
    [
      "新增了创作关卡上传,使用需授权",
      "完善了创作模式的各项功能."
    ] 
  },
  { 
    "版本": "v1.0.1", 
    "日期": "2026-07-07", 
    "内容": 
    [
      "新增了创作模式",
      "修复了游戏时返回再次开始卡住的问题."
    ] 
  },
  { "版本": "v1.0.0", "日期": "2026-07-01", "内容": "首个公测版本" },
  { "版本": "v0.0.2", "日期": "2026-06-01", "内容": "首个可玩版本" },
  { "版本": "v0.0.1", "日期": "2026-05-01", "内容": "首个内测版本" }
]
